package jd.jvmexample.main.classfile.startfromzero;


/**
flags: ACC_PUBLIC, ACC_SUPER
Constant pool:
 #1 = Methodref          #3.#13         // java/lang/Object."<init>":()V
 #2 = Class              #14            // jd/jvmexample/main/classfile/startfromzero/Example002EmptyClassFile
 #3 = Class              #15            // java/lang/Object
 #4 = Utf8               <init>
 #5 = Utf8               ()V
 #6 = Utf8               Code
 #7 = Utf8               LineNumberTable
 #8 = Utf8               LocalVariableTable
 #9 = Utf8               this
 #10 = Utf8               Ljd/jvmexample/main/classfile/startfromzero/ExampleEmptyClassFile;
 #11 = Utf8               SourceFile
 #12 = Utf8               ExampleEmptyClassFile.java
 #13 = NameAndType        #4:#5          // "<init>":()V
 #14 = Utf8               jd/jvmexample/main/classfile/startfromzero/Example002EmptyClassFile
 #15 = Utf8               java/lang/Object

Methods:
 #0: <init>
 descriptor: #5 -> ()V
 flags: ACC_PUBLIC
 stack=1, locals=1, args_size=1
 Code:
 0: aload_0
 1: invokespecial #1                  // Method java/lang/Object."<init>":()V
 4: return
 LineNumberTable:
 line 3: 0
 LocalVariableTable:
 Start  Length  Slot  Name   Signature
 0       5     0  this   Ljd/jvmexample/main/classfile/startfromzero/ExampleEmptyClassFile;
 }

Attributes:
 #0 SourceFile: "ExampleEmptyClassFile.java"

 */
public class Example002EmptyClassFile {
}
